Metadata-Version: 1.0
Name: django-dtpanel-htmltidy
Version: 0.1.1
Summary: Custom panel form Django Debug Toolbar which display HTML Validation errors and warnings
Home-page: https://github.com/joymax/django-dtpanel-htmltidy
Author: Max Klymyshyn
Author-email: klymyshyn@gmail.com
License: BSD
Download-URL: https://github.com/joymax/django-dtpanel-htmltidy/downloads
Platform: UNKNOWN
Classifier: Development Status :: 4 - Beta
Classifier: Environment :: Web Environment
Classifier: Framework :: Django
Classifier: Intended Audience :: Developers
Classifier: License :: OSI Approved :: BSD License
Classifier: Operating System :: OS Independent
Classifier: Programming Language :: Python
Classifier: Topic :: Software Development :: Libraries :: Python Modules
